booking_gauger_dashapp/__init__.py
booking_gauger_dashapp/__main__.py
booking_gauger_dashapp/app.py
booking_gauger_dashapp/constant.py
booking_gauger_dashapp/helper_components.py
booking_gauger_dashapp/predictions_ui.py
booking_gauger_dashapp/style.py
booking_gauger_dashapp/test.py
booking_gauger_dashapp/utils.py
booking_gauger_dashapp-0.0.1.dist-info/LICENSE
booking_gauger_dashapp-0.0.1.dist-info/METADATA
booking_gauger_dashapp-0.0.1.dist-info/WHEEL
booking_gauger_dashapp-0.0.1.dist-info/top_level.txt
booking_gauger_dashapp-0.0.1.dist-info/RECORD
