Metadata-Version: 2.1
Name: booking-gauger-dashapp
Version: 0.0.1
Summary: This package is a web application providing a user interface for                     making predictions on number of accommodation days that an online visitor                     is likely to book. It is intended to be used with the booking_gauger packaging                     which provides the machine learning API for the prediction. The application self-contained                     as it runs out of the box using the a saved model developed with booking_gauger
Home-page: UNKNOWN
Author: Agbleze Linus
Author-email: UNKNOWN
License: MIT
Platform: UNKNOWN
